pip_project_template/__init__.py
pip_project_template/__main__.py
pip_project_template/cli/_GlobalArgumentParser.py
pip_project_template/cli/__init__.py
pip_project_template/cli/calculate.py
pip_project_template/cli/info.py
pip_project_template/cli/serve01.py
pip_project_template/cli/serve02.py
pip_project_template/core/_Calculator.py
pip_project_template/core/__init__.py
pip_project_template/mcp_servers/McpServer01.py
pip_project_template/mcp_servers/McpServer02.py
pip_project_template/types/_DataContainer.py
pip_project_template/types/__init__.py
pip_project_template/utils/__init__.py
pip_project_template/utils/_add.py
pip_project_template/utils/_multiply.py
pip_project_template-0.1.0.dist-info/METADATA
pip_project_template-0.1.0.dist-info/WHEEL
pip_project_template-0.1.0.dist-info/top_level.txt
pip_project_template-0.1.0.dist-info/RECORD
