Metadata-Version: 2.4
Name: pip-project-template
Version: 0.1.0
Summary: A Python project template for a pip package with MCP server support and agentic coding workflows (planning + test-driven development)
Author-email: Yusuke Watanabe <Yusuke.Watanabe@scitex.ai>
Maintainer-email: Yusuke Watanabe <Yusuke.Watanabe@scitex.ai>
License-Expression: MIT
Project-URL: Homepage, https://github.com/ywatanabe1989/pip-project-template
Project-URL: Repository, https://github.com/ywatanabe1989/pip-project-template
Project-URL: Documentation, https://github.com/ywatanabe1989/pip-project-template
Keywords: vibe coding,AI agent,mcp,planning,test-driven development,TDD,template,testing,coverage
Classifier: Development Status :: 4 - Beta
Classifier: Intended Audience :: Developers
Classifier: Operating System :: OS Independent
Classifier: Programming Language :: Python :: 3
Classifier: Programming Language :: Python :: 3.11
Classifier: Programming Language :: Python :: 3.12
Classifier: Topic :: Software Development :: Libraries :: Python Modules
Classifier: Topic :: Communications
Requires-Python: >=3.11
Requires-Dist: pandas>=2.0.0
Requires-Dist: pytest>=8.0.0
Requires-Dist: pytest-cov>=5.0.0
Requires-Dist: pytest-xdist>=3.0.0
Requires-Dist: pytest-testmon>=2.0.0
Requires-Dist: fastmcp>=2.0.0
Provides-Extra: dev
Requires-Dist: ruff>=0.7.0; extra == "dev"
Requires-Dist: mypy>=1.13.0; extra == "dev"
Requires-Dist: pytest-cov>=5.0.0; extra == "dev"
Requires-Dist: pytest-json-report>=1.5.0; extra == "dev"
Requires-Dist: pytest-asyncio>=0.24.0; extra == "dev"
Requires-Dist: pytest-watch>=4.2.0; extra == "dev"
Requires-Dist: pre-commit>=3.5.0; extra == "dev"
Requires-Dist: build>=1.0.0; extra == "dev"
Requires-Dist: twine>=5.0.0; extra == "dev"
